scrape_google/__init__.py
scrape_google-0.0.2.dist-info/LICENSE
scrape_google-0.0.2.dist-info/METADATA
scrape_google-0.0.2.dist-info/WHEEL
scrape_google-0.0.2.dist-info/top_level.txt
scrape_google-0.0.2.dist-info/RECORD
