Metadata-Version: 2.1
Name: scrape-google
Version: 0.0.2
Summary: A package used to scrape top links from google
Home-page: https://github.com/sourabhjain19/scraping
Author: Sourabh Jain
Author-email: sourabhjain1991999@gmail.com
License: UNKNOWN
Download-URL: https://github.com/sourabhjain19/scraping/archive/v1.0.tar.gz
Keywords: scrape,google,scraping,links,crawling,crawl,web scraping,web,search,google search
Platform: UNKNOWN
Classifier: Programming Language :: Python :: 3
Classifier: License :: OSI Approved :: MIT License
Classifier: Operating System :: OS Independent
Requires-Python: >=3.0
Requires-Dist: bs4
Requires-Dist: requests
